cppyy_backend-1.4.2.data/platlib/cppyy_backend/lib/libcppyy_backend.so
cppyy_backend-1.4.2.dist-info/LICENSE.txt
cppyy_backend-1.4.2.dist-info/METADATA
cppyy_backend-1.4.2.dist-info/RECORD
cppyy_backend-1.4.2.dist-info/WHEEL
cppyy_backend-1.4.2.dist-info/top_level.txt
