Metadata-Version: 2.1
Name: cppyy-backend
Version: 1.4.2
Summary: C/C++ wrapper for Cling
Home-page: http://pypy.org
Author: PyPy Developers
Author-email: pypy-dev@python.org
License: LBNL BSD
Keywords: C++ bindings data science
Platform: UNKNOWN
Classifier: Development Status :: 5 - Production/Stable
Classifier: Intended Audience :: Developers
Classifier: Intended Audience :: Science/Research
Classifier: Topic :: Software Development
Classifier: Topic :: Software Development :: Interpreters
Classifier: License :: OSI Approved :: BSD License
Classifier: Operating System :: POSIX
Classifier: Operating System :: POSIX :: Linux
Classifier: Operating System :: MacOS :: MacOS X
Classifier: Programming Language :: C
Classifier: Programming Language :: C++
Classifier: Natural Language :: English
Requires-Dist: cppyy-cling
